setup.py
pintium/__init__.py
pintium/bot.py
pintium.egg-info/PKG-INFO
pintium.egg-info/SOURCES.txt
pintium.egg-info/dependency_links.txt
pintium.egg-info/requires.txt
pintium.egg-info/top_level.txt
pintium/clients/__init__.py
pintium/clients/api_client.py
pintium/clients/bot_client.py
pintium/clients/easy_client.py
pintium/widgets/__init__.py