Metadata-Version: 1.0
Name: pintium
Version: 1.0.0
Summary: Pinterest + Selenium = Pintium
Home-page: UNKNOWN
Author: Brian Lauber
Author-email: constructible.truth@gmail.com
License: UNKNOWN
Platform: UNKNOWN
